odoo9_addon_quality_control_issue-9.0.1.0.0.99.dev7-nspkg.pth
odoo_addons/quality_control_issue/README.rst
odoo_addons/quality_control_issue/__init__.py
odoo_addons/quality_control_issue/__openerp__.py
odoo_addons/quality_control_issue/data/qc_issue_sequence.xml
odoo_addons/quality_control_issue/data/qc_stage_data.xml
odoo_addons/quality_control_issue/i18n/quality_control_issue.pot
odoo_addons/quality_control_issue/models/__init__.py
odoo_addons/quality_control_issue/models/qc_issue.py
odoo_addons/quality_control_issue/models/qc_issue_stage.py
odoo_addons/quality_control_issue/models/qc_problem.py
odoo_addons/quality_control_issue/models/qc_problem_group.py
odoo_addons/quality_control_issue/models/qc_stage.py
odoo_addons/quality_control_issue/models/stock_scrap.py
odoo_addons/quality_control_issue/security/ir.model.access.csv
odoo_addons/quality_control_issue/security/quality_control_issue_security.xml
odoo_addons/quality_control_issue/static/description/icon.png
odoo_addons/quality_control_issue/static/description/icon.svg
odoo_addons/quality_control_issue/views/qc_issue_view.xml
odoo_addons/quality_control_issue/views/qc_problem_group_view.xml
odoo_addons/quality_control_issue/views/qc_problem_view.xml
odoo_addons/quality_control_issue/views/qc_team_dashboard_view.xml
odoo_addons/quality_control_issue/views/stock_scrap_view.xml
odoo9_addon_quality_control_issue-9.0.1.0.0.99.dev7.dist-info/METADATA
odoo9_addon_quality_control_issue-9.0.1.0.0.99.dev7.dist-info/WHEEL
odoo9_addon_quality_control_issue-9.0.1.0.0.99.dev7.dist-info/namespace_packages.txt
odoo9_addon_quality_control_issue-9.0.1.0.0.99.dev7.dist-info/top_level.txt
odoo9_addon_quality_control_issue-9.0.1.0.0.99.dev7.dist-info/RECORD
